bandcamp_get-0.1.4.dist-info/entry_points.txt
bandcamp_get-0.1.4.dist-info/metadata.json
bandcamp_get-0.1.4.dist-info/RECORD
bandcamp_get-0.1.4.dist-info/top_level.txt
bandcamp_get-0.1.4.dist-info/DESCRIPTION.rst
bandcamp_get-0.1.4.dist-info/WHEEL
bandcamp_get-0.1.4.dist-info/METADATA
bandcamp_get/__init__.py
bandcamp_get/bandcamp_get.py
