Metadata-Version: 2.0
Name: bandcamp-get
Version: 0.1.4
Summary: automated music downloading via selenium
Home-page: https://github.com/huntrar/bandcamp-get
Author: Hunter Hammond
Author-email: huntrar@gmail.com
License: MIT
Keywords: bandcamp-get bandcamp free music download guerrilla mail selenium webdriver downloader automated
Platform: UNKNOWN
Classifier: Development Status :: 5 - Production/Stable
Classifier: Environment :: Console
Classifier: Environment :: Web Environment
Classifier: Intended Audience :: End Users/Desktop
Classifier: Programming Language :: Python :: 2
Classifier: Programming Language :: Python :: 2.6
Classifier: Programming Language :: Python :: 2.7
Classifier: Programming Language :: Python :: 3
Classifier: Programming Language :: Python :: 3.2
Classifier: Programming Language :: Python :: 3.3
Classifier: Programming Language :: Python :: 3.4
Requires-Dist: lxml
Requires-Dist: requests
